geostatspy/GSLIB.py
geostatspy/__init__.py
geostatspy/geostats.py
geostatspy-0.0.79.dist-info/LICENSE
geostatspy-0.0.79.dist-info/METADATA
geostatspy-0.0.79.dist-info/WHEEL
geostatspy-0.0.79.dist-info/top_level.txt
geostatspy-0.0.79.dist-info/RECORD
