Metadata-Version: 2.1
Name: geostatspy
Version: 0.0.79
Summary: Open-source spatial data analytics and geostatistics methods in Python.
Author-email: Michael Pyrcz <mpyrcz@austin.utexas.edu>
License: MIT
Project-URL: Source, https://github.com/GeostatsGuy/GeostatsPy
Keywords: geostatistics,spatial data analytics
Classifier: Intended Audience :: Science/Research
Classifier: License :: OSI Approved :: MIT License
Classifier: Operating System :: OS Independent
Classifier: Programming Language :: Python :: 3
Requires-Python: >=3.7
License-File: LICENSE
